llm_cli_lite/__init__.py
llm_cli_lite/__main__.py
llm_cli_lite/config.example.json
llm_cli_lite/openai_api.py
llm_cli_lite/openai_api_fun.py
llm_cli_lite-1.0.2.dist-info/licenses/LICENSE
llm_cli_lite-1.0.2.dist-info/METADATA
llm_cli_lite-1.0.2.dist-info/WHEEL
llm_cli_lite-1.0.2.dist-info/entry_points.txt
llm_cli_lite-1.0.2.dist-info/top_level.txt
llm_cli_lite-1.0.2.dist-info/RECORD
