Metadata-Version: 2.4
Name: llm-cli-lite
Version: 1.0.2
Summary: A lightweight command-line tool that generates terminal commands from natural language
Author: mr_hanlu
License: MIT License
Project-URL: Homepage, https://github.com/mr-hanlu/llm-cli-lite
Classifier: Programming Language :: Python :: 3.12
Classifier: License :: OSI Approved :: MIT License
Requires-Python: >=3.10
License-File: LICENSE
Requires-Dist: openai>=1.77.0
Requires-Dist: rich>=14.0.0
Requires-Dist: importlib_metadata>=8.5.0
Dynamic: license-file
